mangopay/__init__.py
mangopay/api.py
mangopay/auth.py
mangopay/base.py
mangopay/compat.py
mangopay/constants.py
mangopay/exceptions.py
mangopay/fields.py
mangopay/page.py
mangopay/query.py
mangopay/ratelimit.py
mangopay/resources.py
mangopay/signals.py
mangopay/utils.py
mangopay4_python_sdk-3.53.0.dist-info/licenses/LICENSE
mangopay4_python_sdk-3.53.0.dist-info/METADATA
mangopay4_python_sdk-3.53.0.dist-info/WHEEL
mangopay4_python_sdk-3.53.0.dist-info/entry_points.txt
mangopay4_python_sdk-3.53.0.dist-info/top_level.txt
mangopay4_python_sdk-3.53.0.dist-info/RECORD
