Metadata-Version: 2.4
Name: mangopay4-python-sdk
Version: 3.53.0
Summary: A client library written in python to work with mangopay v2 api
Home-page: https://github.com/Mangopay/mangopay2-python-sdk
Author: Mangopay (www.mangopay.com)
Author-email: support@mangopay.com
License: MIT
Keywords: mangopay api development emoney sdk
Classifier: Intended Audience :: Developers
Classifier: Topic :: Software Development :: Build Tools
Classifier: License :: OSI Approved :: MIT License
Classifier: Programming Language :: Python :: 3.9
Classifier: Programming Language :: Python :: 3.10
Classifier: Programming Language :: Python :: 3.11
Classifier: Programming Language :: Python :: 3.12
License-File: LICENSE
Requires-Dist: requests
Requires-Dist: simplejson
Requires-Dist: blinker
Requires-Dist: six
Requires-Dist: pytz
Provides-Extra: dev
Requires-Dist: responses; extra == "dev"
Requires-Dist: nose; extra == "dev"
Requires-Dist: coverage; extra == "dev"
Requires-Dist: httplib2; extra == "dev"
Requires-Dist: pyopenssl; extra == "dev"
Requires-Dist: ndg-httpsclient; extra == "dev"
Requires-Dist: pyasn1; extra == "dev"
Requires-Dist: exam; extra == "dev"
Provides-Extra: test
Requires-Dist: responses; extra == "test"
Requires-Dist: nose; extra == "test"
Requires-Dist: coverage; extra == "test"
Requires-Dist: httplib2; extra == "test"
Requires-Dist: pyopenssl; extra == "test"
Requires-Dist: ndg-httpsclient; extra == "test"
Requires-Dist: pyasn1; extra == "test"
Requires-Dist: exam; extra == "test"
Dynamic: author
Dynamic: author-email
Dynamic: classifier
Dynamic: description
Dynamic: home-page
Dynamic: keywords
Dynamic: license
Dynamic: license-file
Dynamic: provides-extra
Dynamic: requires-dist
Dynamic: summary
